scapex/__init__.py
scapex/cli.py
scapex/config.py
scapex/constants.py
scapex/exporter.py
scapex/log.py
scapex/zsh/_scapex
scapex-1.0.1.dist-info/licenses/LICENSE
scapex-1.0.1.dist-info/METADATA
scapex-1.0.1.dist-info/WHEEL
scapex-1.0.1.dist-info/entry_points.txt
scapex-1.0.1.dist-info/top_level.txt
scapex-1.0.1.dist-info/RECORD
