Metadata-Version: 2.4
Name: scapex
Version: 1.0.1
Summary: The command-line Inkscape eXporter, Makefile and LaTeX friendly
Author-email: Pierre Ayoub <pierreay@proton.me>
License-Expression: GPL-3.0-only
Project-URL: Homepage, https://github.com/pierreay/scapex
Project-URL: Issues, https://github.com/pierreay/scapex/issues
Classifier: Programming Language :: Python :: 3
Classifier: Operating System :: POSIX :: Linux
Classifier: Development Status :: 5 - Production/Stable
Classifier: Topic :: Utilities
License-File: LICENSE
Dynamic: license-file
